hn/__init__.py
hn/cli.py
hn_cli-1.0.0.dist-info/DESCRIPTION.rst
hn_cli-1.0.0.dist-info/METADATA
hn_cli-1.0.0.dist-info/RECORD
hn_cli-1.0.0.dist-info/WHEEL
hn_cli-1.0.0.dist-info/entry_points.txt
hn_cli-1.0.0.dist-info/metadata.json
hn_cli-1.0.0.dist-info/top_level.txt
